Metadata-Version: 2.4
Name: ckanext-saml
Version: 0.3.10
Author-email: DataShades <datashades@linkdigital.com.au>, Yan Rudendo <yan.rudenko@linkdigital.com.au>, Sergey Motornyuk <sergey.motornyuk@linkdigital.com.au>
Maintainer-email: DataShades <datashades@linkdigital.com.au>
License: AGPL
Project-URL: Homepage, https://github.com/DataShades/ckanext-saml
Keywords: CKAN
Classifier: Development Status :: 4 - Beta
Classifier: License :: OSI Approved :: GNU Affero General Public License v3 or later (AGPLv3+)
Classifier: Programming Language :: Python :: 3.7
Classifier: Programming Language :: Python :: 3.8
Classifier: Programming Language :: Python :: 3.9
Classifier: Programming Language :: Python :: 3.10
Requires-Python: >=3.7
License-File: LICENSE
Requires-Dist: python3-saml
Requires-Dist: typing-extensions
Requires-Dist: ckanext-toolbelt
Provides-Extra: adfs
Requires-Dist: lxml==4.6.4; extra == "adfs"
Dynamic: license-file
